{
  "experiment_name": "experiment_grid_lr0.005_wd0.001_s42_20251129_230209",
  "experiment_dir": "/Users/ema/projects/DL4SE-project-UPM/code/experiments/results/experiment_grid_lr0.005_wd0.001_s42_20251129_230209",
  "timestamp": "2025-11-29T23:47:20.700721",
  "model": "ConvNextTiny",
  "loss": "CrossEntropyLossWrapper",
  "loss_params": {
    "weight": null,
    "reduction": "mean"
  },
  "best_epoch": 16,
  "split_info": {
    "train": {
      "total_samples": 15283,
      "class_counts": {
        "no_defect": 7752,
        "defect": 7531
      }
    },
    "val": {
      "total_samples": 3275,
      "class_counts": {
        "no_defect": 1661,
        "defect": 1614
      }
    },
    "test": {
      "total_samples": 3277,
      "class_counts": {
        "no_defect": 1662,
        "defect": 1615
      }
    },
    "total": {
      "total_samples": 21835,
      "class_counts": {
        "no_defect": 11075,
        "defect": 10760
      }
    }
  },
  "config": {
    "model": {
      "name": "convnext_tiny",
      "num_classes": 2,
      "pretrained": true,
      "cbam_stages": [
        3,
        4
      ]
    },
    "loss": {
      "type": "cross_entropy",
      "weight": null,
      "reduction": "mean"
    },
    "data": {
      "img_dir": "data/images",
      "ann_dir": "data/annotations",
      "splits_dir": "data/splits",
      "batch_size": 64,
      "num_workers": 0,
      "pin_memory": false,
      "image_size": [
        150,
        150
      ],
      "num_classes": 2,
      "class_names": [
        "no_defect",
        "defect"
      ],
      "split_strategy": "stratified_70_15_15",
      "use_saved_splits": true
    },
    "augmentation": {
      "horizontal_flip": 0.5,
      "vertical_flip": 0.3,
      "rotation": 10,
      "brightness_contrast": {
        "brightness": 0.2,
        "contrast": 0.2
      },
      "defect_blackout": {
        "enabled": false
      }
    },
    "training": {
      "num_epochs": 50,
      "learning_rate": 0.005,
      "weight_decay": 0.001,
      "warmup_epochs": 2,
      "early_stopping_patience": 5,
      "early_stopping_metric": "f1_macro",
      "log_interval": 5,
      "threshold": 0.5,
      "save_checkpoints": false,
      "freeze_backbone": true,
      "freeze_early_stages": null
    },
    "optimizer": {
      "type": "adamw",
      "lr": 0.005,
      "weight_decay": 0.001,
      "betas": [
        0.9,
        0.999
      ]
    },
    "scheduler": {
      "type": "cosine",
      "warmup_epochs": 3
    },
    "experiment": {
      "name": "grid_lr0.005_wd0.001_s42",
      "seed": 42,
      "save_dir": "code/experiments/results",
      "output_dir": "/Users/ema/projects/DL4SE-project-UPM/code/experiments/results/experiment_grid_lr0.005_wd0.001_s42_20251129_230209"
    }
  },
  "device": "mps",
  "num_model_parameters": 28590666,
  "num_trainable_parameters": 772074,
  "best_val_metrics": {
    "precision_macro": 0.9643041483178786,
    "recall_macro": 0.9643945548694557,
    "f1_macro": 0.9642737299400734,
    "precision_micro": 0.9642748091603054,
    "recall_micro": 0.9642748091603054,
    "f1_micro": 0.9642748091603054,
    "accuracy": 0.9642748091603054,
    "hamming_loss": 0.03572519083969466,
    "no_defect_precision": 0.9730392156862745,
    "no_defect_recall": 0.9560505719446116,
    "no_defect_f1": 0.9644700880655936,
    "no_defect_tp": 1588,
    "no_defect_fp": 44,
    "no_defect_tn": 1570,
    "no_defect_fn": 73,
    "no_defect_support": 1661,
    "defect_precision": 0.9555690809494827,
    "defect_recall": 0.9727385377942999,
    "defect_f1": 0.9640773718145532,
    "defect_tp": 1570,
    "defect_fp": 73,
    "defect_tn": 1588,
    "defect_fn": 44,
    "defect_support": 1614
  },
  "test_metrics": {
    "precision_macro": 0.9623919195534726,
    "recall_macro": 0.9620301550222977,
    "f1_macro": 0.9621406817636351,
    "precision_micro": 0.9621605126640219,
    "recall_micro": 0.9621605126640219,
    "f1_micro": 0.9621605126640219,
    "accuracy": 0.9621605126640219,
    "hamming_loss": 0.03783948733597803,
    "no_defect_precision": 0.9550295857988166,
    "no_defect_recall": 0.9711191335740073,
    "no_defect_f1": 0.9630071599045346,
    "no_defect_tp": 1614,
    "no_defect_fp": 76,
    "no_defect_tn": 1539,
    "no_defect_fn": 48,
    "no_defect_support": 1662,
    "defect_precision": 0.9697542533081286,
    "defect_recall": 0.9529411764705882,
    "defect_f1": 0.9612742036227357,
    "defect_tp": 1539,
    "defect_fp": 48,
    "defect_tn": 1614,
    "defect_fn": 76,
    "defect_support": 1615
  },
  "training_history": {
    "epoch": [
      1,
      2,
      3,
      4,
      5,
      6,
      7,
      8,
      9,
      10,
      11,
      12,
      13,
      14,
      15,
      16,
      17,
      18,
      19,
      20,
      21
    ],
    "train_loss": [
      0.4605222965384128,
      0.2537239202021555,
      0.19727972523936665,
      0.1782170829351477,
      0.166862764617888,
      0.17696431025114517,
      0.1687968100370473,
      0.1664356172677114,
      0.17340547317116828,
      0.17356234679785731,
      0.16570167756292611,
      0.17383687311947096,
      0.17188230766349757,
      0.16780946835501423,
      0.17157903045540573,
      0.16911459651826316,
      0.170437059579534,
      0.16990629232889937,
      0.16649304428546996,
      0.17259615444613302,
      0.17147995646123357
    ],
    "val_loss": [
      0.37315556005789685,
      0.19892854530077714,
      0.1620704343972298,
      0.13423356198920652,
      0.13949063083586785,
      0.12429192762535352,
      0.11651322811555404,
      0.11508105544803235,
      0.11233026455514707,
      0.11431488000716154,
      0.11392055781414875,
      0.11495346167626289,
      0.11150281998113944,
      0.12309241588585652,
      0.11271070337925966,
      0.1109123956412077,
      0.10770106903062417,
      0.11061523783092315,
      0.1139066991611169,
      0.1119748896990831,
      0.1081775681187327
    ]
  },
  "metrics_history": {
    "epoch": [
      1,
      2,
      3,
      4,
      5,
      6,
      7,
      8,
      9,
      10,
      11,
      12,
      13,
      14,
      15,
      16,
      17,
      18,
      19,
      20,
      21
    ],
    "train_metrics": [
      null,
      null,
      null,
      null,
      null,
      null,
      null,
      null,
      null,
      null,
      null,
      null,
      null,
      null,
      null,
      null,
      null,
      null,
      null,
      null,
      null
    ],
    "val_metrics": [
      {
        "precision_macro": 0.8959277893983078,
        "recall_macro": 0.8918658009723768,
        "f1_macro": 0.8921522621455937,
        "precision_micro": 0.8925190839694657,
        "recall_micro": 0.8925190839694657,
        "f1_micro": 0.8925190839694657,
        "accuracy": 0.8925190839694657,
        "hamming_loss": 0.10748091603053435,
        "no_defect_precision": 0.8626038781163435,
        "no_defect_recall": 0.9373871161950632,
        "no_defect_f1": 0.8984420080784766,
        "no_defect_tp": 1557,
        "no_defect_fp": 248,
        "no_defect_tn": 1366,
        "no_defect_fn": 104,
        "no_defect_support": 1661,
        "defect_precision": 0.9292517006802721,
        "defect_recall": 0.8463444857496902,
        "defect_f1": 0.8858625162127107,
        "defect_tp": 1366,
        "defect_fp": 104,
        "defect_tn": 1557,
        "defect_fn": 248,
        "defect_support": 1614
      },
      {
        "precision_macro": 0.940605562508172,
        "recall_macro": 0.9399474943432204,
        "f1_macro": 0.9401064293541385,
        "precision_micro": 0.9401526717557251,
        "recall_micro": 0.9401526717557251,
        "f1_micro": 0.9401526717557251,
        "accuracy": 0.9401526717557251,
        "hamming_loss": 0.05984732824427481,
        "no_defect_precision": 0.9296187683284457,
        "no_defect_recall": 0.9542444310656231,
        "no_defect_f1": 0.9417706476530006,
        "no_defect_tp": 1585,
        "no_defect_fp": 120,
        "no_defect_tn": 1494,
        "no_defect_fn": 76,
        "no_defect_support": 1661,
        "defect_precision": 0.9515923566878981,
        "defect_recall": 0.9256505576208178,
        "defect_f1": 0.9384422110552764,
        "defect_tp": 1494,
        "defect_fp": 76,
        "defect_tn": 1585,
        "defect_fn": 120,
        "defect_support": 1614
      },
      {
        "precision_macro": 0.9428563865496997,
        "recall_macro": 0.9399592443303515,
        "f1_macro": 0.940319107389721,
        "precision_micro": 0.9404580152671755,
        "recall_micro": 0.9404580152671755,
        "f1_micro": 0.9404580152671755,
        "accuracy": 0.9404580152671755,
        "hamming_loss": 0.059541984732824425,
        "no_defect_precision": 0.9136568848758465,
        "no_defect_recall": 0.9747140276941602,
        "no_defect_f1": 0.9431983687736674,
        "no_defect_tp": 1619,
        "no_defect_fp": 153,
        "no_defect_tn": 1461,
        "no_defect_fn": 42,
        "no_defect_support": 1661,
        "defect_precision": 0.9720558882235529,
        "defect_recall": 0.9052044609665427,
        "defect_f1": 0.9374398460057748,
        "defect_tp": 1461,
        "defect_fp": 42,
        "defect_tn": 1619,
        "defect_fn": 153,
        "defect_support": 1614
      },
      {
        "precision_macro": 0.955413656427752,
        "recall_macro": 0.9555070884128714,
        "f1_macro": 0.9554172494172495,
        "precision_micro": 0.9554198473282443,
        "recall_micro": 0.9554198473282443,
        "f1_micro": 0.9554198473282443,
        "accuracy": 0.9554198473282443,
        "hamming_loss": 0.044580152671755725,
        "no_defect_precision": 0.9621720561317877,
        "no_defect_recall": 0.9494280553883203,
        "no_defect_f1": 0.9557575757575758,
        "no_defect_tp": 1577,
        "no_defect_fp": 62,
        "no_defect_tn": 1552,
        "no_defect_fn": 84,
        "no_defect_support": 1661,
        "defect_precision": 0.9486552567237164,
        "defect_recall": 0.9615861214374225,
        "defect_f1": 0.955076923076923,
        "defect_tp": 1552,
        "defect_fp": 84,
        "defect_tn": 1577,
        "defect_fn": 62,
        "defect_support": 1614
      },
      {
        "precision_macro": 0.9539122315592904,
        "recall_macro": 0.9533443447498446,
        "f1_macro": 0.9529704299771804,
        "precision_micro": 0.9529770992366412,
        "recall_micro": 0.9529770992366412,
        "f1_micro": 0.9529770992366412,
        "accuracy": 0.9529770992366412,
        "hamming_loss": 0.04702290076335878,
        "no_defect_precision": 0.9784126984126984,
        "no_defect_recall": 0.9277543648404576,
        "no_defect_f1": 0.9524103831891224,
        "no_defect_tp": 1541,
        "no_defect_fp": 34,
        "no_defect_tn": 1580,
        "no_defect_fn": 120,
        "no_defect_support": 1661,
        "defect_precision": 0.9294117647058824,
        "defect_recall": 0.9789343246592317,
        "defect_f1": 0.9535304767652384,
        "defect_tp": 1580,
        "defect_fp": 120,
        "defect_tn": 1541,
        "defect_fn": 34,
        "defect_support": 1614
      },
      {
        "precision_macro": 0.9563651274569475,
        "recall_macro": 0.9564539881694416,
        "f1_macro": 0.9563345588156453,
        "precision_micro": 0.9563358778625954,
        "recall_micro": 0.9563358778625954,
        "f1_micro": 0.9563358778625954,
        "accuracy": 0.9563358778625954,
        "hamming_loss": 0.04366412213740458,
        "no_defect_precision": 0.9650735294117647,
        "no_defect_recall": 0.9482239614689946,
        "no_defect_f1": 0.9565745520801701,
        "no_defect_tp": 1575,
        "no_defect_fp": 57,
        "no_defect_tn": 1557,
        "no_defect_fn": 86,
        "no_defect_support": 1661,
        "defect_precision": 0.9476567255021302,
        "defect_recall": 0.9646840148698885,
        "defect_f1": 0.9560945655511207,
        "defect_tp": 1557,
        "defect_fp": 86,
        "defect_tn": 1575,
        "defect_fn": 57,
        "defect_support": 1614
      },
      {
        "precision_macro": 0.9605832620964674,
        "recall_macro": 0.960642019296836,
        "f1_macro": 0.9606053832922066,
        "precision_micro": 0.9606106870229008,
        "recall_micro": 0.9606106870229008,
        "f1_micro": 0.9606106870229008,
        "accuracy": 0.9606106870229008,
        "hamming_loss": 0.03938931297709924,
        "no_defect_precision": 0.9636803874092009,
        "no_defect_recall": 0.9584587597832631,
        "no_defect_f1": 0.961062481134923,
        "no_defect_tp": 1592,
        "no_defect_fp": 60,
        "no_defect_tn": 1554,
        "no_defect_fn": 69,
        "no_defect_support": 1661,
        "defect_precision": 0.9574861367837338,
        "defect_recall": 0.9628252788104089,
        "defect_f1": 0.9601482854494903,
        "defect_tp": 1554,
        "defect_fp": 69,
        "defect_tn": 1592,
        "defect_fn": 60,
        "defect_support": 1614
      },
      {
        "precision_macro": 0.9579380653360245,
        "recall_macro": 0.9570064240723293,
        "f1_macro": 0.9572112125474457,
        "precision_micro": 0.9572519083969465,
        "recall_micro": 0.9572519083969465,
        "f1_micro": 0.9572519083969465,
        "accuracy": 0.9572519083969465,
        "hamming_loss": 0.042748091603053436,
        "no_defect_precision": 0.9434402332361516,
        "no_defect_recall": 0.9741119807344973,
        "no_defect_f1": 0.9585308056872038,
        "no_defect_tp": 1618,
        "no_defect_fp": 97,
        "no_defect_tn": 1517,
        "no_defect_fn": 43,
        "no_defect_support": 1661,
        "defect_precision": 0.9724358974358974,
        "defect_recall": 0.9399008674101611,
        "defect_f1": 0.9558916194076874,
        "defect_tp": 1517,
        "defect_fp": 43,
        "defect_tn": 1618,
        "defect_fn": 97,
        "defect_support": 1614
      },
      {
        "precision_macro": 0.9600530330391281,
        "recall_macro": 0.9599435478396063,
        "f1_macro": 0.959987450408081,
        "precision_micro": 0.96,
        "recall_micro": 0.96,
        "f1_micro": 0.96,
        "accuracy": 0.96,
        "hamming_loss": 0.04,
        "no_defect_precision": 0.9575358851674641,
        "no_defect_recall": 0.9638771824202288,
        "no_defect_f1": 0.9606960696069607,
        "no_defect_tp": 1601,
        "no_defect_fp": 71,
        "no_defect_tn": 1543,
        "no_defect_fn": 60,
        "no_defect_support": 1661,
        "defect_precision": 0.9625701809107923,
        "defect_recall": 0.9560099132589839,
        "defect_f1": 0.9592788312092011,
        "defect_tp": 1543,
        "defect_fp": 60,
        "defect_tn": 1601,
        "defect_fn": 71,
        "defect_support": 1614
      },
      {
        "precision_macro": 0.9599776432043399,
        "recall_macro": 0.9600136747469277,
        "f1_macro": 0.9599934202802516,
        "precision_micro": 0.96,
        "recall_micro": 0.96,
        "f1_micro": 0.96,
        "accuracy": 0.96,
        "hamming_loss": 0.04,
        "no_defect_precision": 0.9619565217391305,
        "no_defect_recall": 0.9590608067429259,
        "no_defect_f1": 0.960506481760627,
        "no_defect_tp": 1593,
        "no_defect_fp": 63,
        "no_defect_tn": 1551,
        "no_defect_fn": 68,
        "no_defect_support": 1661,
        "defect_precision": 0.9579987646695491,
        "defect_recall": 0.9609665427509294,
        "defect_f1": 0.9594803587998763,
        "defect_tp": 1551,
        "defect_fp": 68,
        "defect_tn": 1593,
        "defect_fn": 63,
        "defect_support": 1614
      },
      {
        "precision_macro": 0.9608899137587663,
        "recall_macro": 0.960969340366913,
        "f1_macro": 0.9609120618365214,
        "precision_micro": 0.9609160305343512,
        "recall_micro": 0.9609160305343512,
        "f1_micro": 0.9609160305343512,
        "accuracy": 0.9609160305343512,
        "hamming_loss": 0.039083969465648856,
        "no_defect_precision": 0.9653916211293261,
        "no_defect_recall": 0.9572546658639374,
        "no_defect_f1": 0.9613059250302297,
        "no_defect_tp": 1590,
        "no_defect_fp": 57,
        "no_defect_tn": 1557,
        "no_defect_fn": 71,
        "no_defect_support": 1661,
        "defect_precision": 0.9563882063882064,
        "defect_recall": 0.9646840148698885,
        "defect_f1": 0.9605181986428131,
        "defect_tp": 1557,
        "defect_fp": 71,
        "defect_tn": 1590,
        "defect_fn": 57,
        "defect_support": 1614
      },
      {
        "precision_macro": 0.9588785172492678,
        "recall_macro": 0.9579182603752386,
        "f1_macro": 0.9581273218723161,
        "precision_micro": 0.9581679389312977,
        "recall_micro": 0.9581679389312977,
        "f1_micro": 0.9581679389312977,
        "accuracy": 0.9581679389312977,
        "hamming_loss": 0.04183206106870229,
        "no_defect_precision": 0.9440559440559441,
        "no_defect_recall": 0.975316074653823,
        "no_defect_f1": 0.9594314480307966,
        "no_defect_tp": 1620,
        "no_defect_fp": 96,
        "no_defect_tn": 1518,
        "no_defect_fn": 41,
        "no_defect_support": 1661,
        "defect_precision": 0.9737010904425915,
        "defect_recall": 0.9405204460966543,
        "defect_f1": 0.9568231957138355,
        "defect_tp": 1518,
        "defect_fp": 41,
        "defect_tn": 1620,
        "defect_fn": 96,
        "defect_support": 1614
      },
      {
        "precision_macro": 0.9627282614939207,
        "recall_macro": 0.9627579495190712,
        "f1_macro": 0.962741668606282,
        "precision_micro": 0.9627480916030534,
        "recall_micro": 0.9627480916030534,
        "f1_micro": 0.9627480916030534,
        "accuracy": 0.9627480916030534,
        "hamming_loss": 0.037251908396946566,
        "no_defect_precision": 0.9643934821967411,
        "no_defect_recall": 0.9620710415412402,
        "no_defect_f1": 0.9632308619650392,
        "no_defect_tp": 1598,
        "no_defect_fp": 59,
        "no_defect_tn": 1555,
        "no_defect_fn": 63,
        "no_defect_support": 1661,
        "defect_precision": 0.9610630407911002,
        "defect_recall": 0.9634448574969021,
        "defect_f1": 0.9622524752475248,
        "defect_tp": 1555,
        "defect_fp": 63,
        "defect_tn": 1598,
        "defect_fn": 59,
        "defect_support": 1614
      },
      {
        "precision_macro": 0.9567775175644029,
        "recall_macro": 0.9547151765817907,
        "f1_macro": 0.9550369664921381,
        "precision_micro": 0.9551145038167939,
        "recall_micro": 0.9551145038167939,
        "f1_micro": 0.9551145038167939,
        "accuracy": 0.9551145038167939,
        "hamming_loss": 0.04488549618320611,
        "no_defect_precision": 0.9325714285714286,
        "no_defect_recall": 0.9825406381697772,
        "no_defect_f1": 0.9569041336851363,
        "no_defect_tp": 1632,
        "no_defect_fp": 118,
        "no_defect_tn": 1496,
        "no_defect_fn": 29,
        "no_defect_support": 1661,
        "defect_precision": 0.980983606557377,
        "defect_recall": 0.9268897149938042,
        "defect_f1": 0.9531697992991398,
        "defect_tp": 1496,
        "defect_fp": 29,
        "defect_tn": 1632,
        "defect_fn": 118,
        "defect_support": 1614
      },
      {
        "precision_macro": 0.9605858501775608,
        "recall_macro": 0.9606683168870815,
        "f1_macro": 0.9606069260758512,
        "precision_micro": 0.9606106870229008,
        "recall_micro": 0.9606106870229008,
        "f1_micro": 0.9606106870229008,
        "accuracy": 0.9606106870229008,
        "hamming_loss": 0.03938931297709924,
        "no_defect_precision": 0.965370595382746,
        "no_defect_recall": 0.9566526189042746,
        "no_defect_f1": 0.9609918355004535,
        "no_defect_tp": 1589,
        "no_defect_fp": 57,
        "no_defect_tn": 1557,
        "no_defect_fn": 72,
        "no_defect_support": 1661,
        "defect_precision": 0.9558011049723757,
        "defect_recall": 0.9646840148698885,
        "defect_f1": 0.9602220166512488,
        "defect_tp": 1557,
        "defect_fp": 72,
        "defect_tn": 1589,
        "defect_fn": 57,
        "defect_support": 1614
      },
      {
        "precision_macro": 0.9643041483178786,
        "recall_macro": 0.9643945548694557,
        "f1_macro": 0.9642737299400734,
        "precision_micro": 0.9642748091603054,
        "recall_micro": 0.9642748091603054,
        "f1_micro": 0.9642748091603054,
        "accuracy": 0.9642748091603054,
        "hamming_loss": 0.03572519083969466,
        "no_defect_precision": 0.9730392156862745,
        "no_defect_recall": 0.9560505719446116,
        "no_defect_f1": 0.9644700880655936,
        "no_defect_tp": 1588,
        "no_defect_fp": 44,
        "no_defect_tn": 1570,
        "no_defect_fn": 73,
        "no_defect_support": 1661,
        "defect_precision": 0.9555690809494827,
        "defect_recall": 0.9727385377942999,
        "defect_f1": 0.9640773718145532,
        "defect_tp": 1570,
        "defect_fp": 73,
        "defect_tn": 1588,
        "defect_fn": 44,
        "defect_support": 1614
      },
      {
        "precision_macro": 0.9627404177922408,
        "recall_macro": 0.9627404177922408,
        "f1_macro": 0.9627404177922408,
        "precision_micro": 0.9627480916030534,
        "recall_micro": 0.9627480916030534,
        "f1_micro": 0.9627480916030534,
        "accuracy": 0.9627480916030534,
        "hamming_loss": 0.037251908396946566,
        "no_defect_precision": 0.963275135460566,
        "no_defect_recall": 0.963275135460566,
        "no_defect_f1": 0.963275135460566,
        "no_defect_tp": 1600,
        "no_defect_fp": 61,
        "no_defect_tn": 1553,
        "no_defect_fn": 61,
        "no_defect_support": 1661,
        "defect_precision": 0.9622057001239157,
        "defect_recall": 0.9622057001239157,
        "defect_f1": 0.9622057001239157,
        "defect_tp": 1553,
        "defect_fp": 61,
        "defect_tn": 1600,
        "defect_fn": 61,
        "defect_support": 1614
      },
      {
        "precision_macro": 0.9624207031238343,
        "recall_macro": 0.9624569260392397,
        "f1_macro": 0.9624365701868012,
        "precision_micro": 0.962442748091603,
        "recall_micro": 0.962442748091603,
        "f1_micro": 0.962442748091603,
        "accuracy": 0.962442748091603,
        "hamming_loss": 0.03755725190839695,
        "no_defect_precision": 0.9643719806763285,
        "no_defect_recall": 0.9614689945815773,
        "no_defect_f1": 0.962918299668375,
        "no_defect_tp": 1597,
        "no_defect_fp": 59,
        "no_defect_tn": 1555,
        "no_defect_fn": 64,
        "no_defect_support": 1661,
        "defect_precision": 0.9604694255713403,
        "defect_recall": 0.9634448574969021,
        "defect_f1": 0.9619548407052273,
        "defect_tp": 1555,
        "defect_fp": 64,
        "defect_tn": 1597,
        "defect_fn": 59,
        "defect_support": 1614
      },
      {
        "precision_macro": 0.959019970339525,
        "recall_macro": 0.9578919627849931,
        "f1_macro": 0.9581223974961268,
        "precision_micro": 0.9581679389312977,
        "recall_micro": 0.9581679389312977,
        "f1_micro": 0.9581679389312977,
        "accuracy": 0.9581679389312977,
        "hamming_loss": 0.04183206106870229,
        "no_defect_precision": 0.9425087108013938,
        "no_defect_recall": 0.9771222155328115,
        "no_defect_f1": 0.9595033993496896,
        "no_defect_tp": 1623,
        "no_defect_fp": 99,
        "no_defect_tn": 1515,
        "no_defect_fn": 38,
        "no_defect_support": 1661,
        "defect_precision": 0.9755312298776562,
        "defect_recall": 0.9386617100371747,
        "defect_f1": 0.9567413956425639,
        "defect_tp": 1515,
        "defect_fp": 38,
        "defect_tn": 1623,
        "defect_fn": 99,
        "defect_support": 1614
      },
      {
        "precision_macro": 0.9618390216468686,
        "recall_macro": 0.9619337718503134,
        "f1_macro": 0.9618303386407694,
        "precision_micro": 0.9618320610687023,
        "recall_micro": 0.9618320610687023,
        "f1_micro": 0.9618320610687023,
        "accuracy": 0.9618320610687023,
        "hamming_loss": 0.03816793893129771,
        "no_defect_precision": 0.969437652811736,
        "no_defect_recall": 0.954846478025286,
        "no_defect_f1": 0.962086745526236,
        "no_defect_tp": 1586,
        "no_defect_fp": 50,
        "no_defect_tn": 1564,
        "no_defect_fn": 75,
        "no_defect_support": 1661,
        "defect_precision": 0.9542403904820013,
        "defect_recall": 0.9690210656753407,
        "defect_f1": 0.9615739317553028,
        "defect_tp": 1564,
        "defect_fp": 75,
        "defect_tn": 1586,
        "defect_fn": 50,
        "defect_support": 1614
      },
      {
        "precision_macro": 0.9617070712726051,
        "recall_macro": 0.9614136017851028,
        "f1_macro": 0.9615086267688402,
        "precision_micro": 0.9615267175572519,
        "recall_micro": 0.9615267175572519,
        "f1_micro": 0.9615267175572519,
        "accuracy": 0.9615267175572519,
        "hamming_loss": 0.03847328244274809,
        "no_defect_precision": 0.9554896142433235,
        "no_defect_recall": 0.9692956050571945,
        "no_defect_f1": 0.9623430962343096,
        "no_defect_tp": 1610,
        "no_defect_fp": 75,
        "no_defect_tn": 1539,
        "no_defect_fn": 51,
        "no_defect_support": 1661,
        "defect_precision": 0.9679245283018868,
        "defect_recall": 0.9535315985130112,
        "defect_f1": 0.9606741573033708,
        "defect_tp": 1539,
        "defect_fp": 51,
        "defect_tn": 1610,
        "defect_fn": 75,
        "defect_support": 1614
      }
    ],
    "test_metrics": [
      {
        "precision_macro": 0.9623919195534726,
        "recall_macro": 0.9620301550222977,
        "f1_macro": 0.9621406817636351,
        "precision_micro": 0.9621605126640219,
        "recall_micro": 0.9621605126640219,
        "f1_micro": 0.9621605126640219,
        "accuracy": 0.9621605126640219,
        "hamming_loss": 0.03783948733597803,
        "no_defect_precision": 0.9550295857988166,
        "no_defect_recall": 0.9711191335740073,
        "no_defect_f1": 0.9630071599045346,
        "no_defect_tp": 1614,
        "no_defect_fp": 76,
        "no_defect_tn": 1539,
        "no_defect_fn": 48,
        "no_defect_support": 1662,
        "defect_precision": 0.9697542533081286,
        "defect_recall": 0.9529411764705882,
        "defect_f1": 0.9612742036227357,
        "defect_tp": 1539,
        "defect_fp": 48,
        "defect_tn": 1614,
        "defect_fn": 76,
        "defect_support": 1615
      }
    ]
  }
}