{
  "experiment_name": "experiment_grid_lr0.01_wd0.001_s80_20251207_194457",
  "experiment_dir": "/workspace/BS-Data/code/experiments/results/experiment_grid_lr0.01_wd0.001_s80_20251207_194457",
  "timestamp": "2025-12-07T19:46:53.407814",
  "model": "ConvNextTiny",
  "loss": "CrossEntropyLossWrapper",
  "loss_params": {
    "weight": null,
    "reduction": "mean"
  },
  "best_epoch": 10,
  "split_info": {
    "train": {
      "total_samples": 15284,
      "class_counts": {
        "no_defect": 7734,
        "defect": 7550
      }
    },
    "val": {
      "total_samples": 3275,
      "class_counts": {
        "no_defect": 1691,
        "defect": 1584
      }
    },
    "test": {
      "total_samples": 3276,
      "class_counts": {
        "no_defect": 1650,
        "defect": 1626
      }
    },
    "total": {
      "total_samples": 21835,
      "class_counts": {
        "no_defect": 11075,
        "defect": 10760
      }
    }
  },
  "config": {
    "model": {
      "name": "convnext_tiny",
      "num_classes": 2,
      "pretrained": true,
      "cbam_stages": [
        3,
        4
      ]
    },
    "loss": {
      "type": "cross_entropy",
      "weight": null,
      "reduction": "mean"
    },
    "data": {
      "img_dir": "data/images",
      "ann_dir": "data/annotations",
      "splits_dir": "data/splits",
      "batch_size": 64,
      "num_workers": 8,
      "pin_memory": false,
      "image_size": [
        150,
        150
      ],
      "num_classes": 2,
      "class_names": [
        "no_defect",
        "defect"
      ],
      "split_strategy": "stratified_70_15_15",
      "use_saved_splits": true
    },
    "augmentation": {
      "horizontal_flip": 0.5,
      "vertical_flip": 0.3,
      "rotation": 10,
      "brightness_contrast": {
        "brightness": 0.2,
        "contrast": 0.2
      },
      "defect_blackout": {
        "enabled": false
      }
    },
    "training": {
      "num_epochs": 15,
      "learning_rate": 0.01,
      "weight_decay": 0.001,
      "warmup_epochs": 2,
      "log_interval": 5,
      "threshold": 0.5,
      "save_checkpoints": false,
      "freeze_backbone": true,
      "freeze_early_stages": null
    },
    "optimizer": {
      "type": "adamw",
      "lr": 0.01,
      "weight_decay": 0.001,
      "betas": [
        0.9,
        0.999
      ]
    },
    "scheduler": {
      "type": "cosine",
      "warmup_epochs": 3
    },
    "experiment": {
      "name": "grid_lr0.01_wd0.001_s80",
      "seed": 80,
      "save_dir": "code/experiments/results",
      "output_dir": "/workspace/BS-Data/code/experiments/results/experiment_grid_lr0.01_wd0.001_s80_20251207_194457"
    }
  },
  "device": "cuda",
  "num_model_parameters": 28590666,
  "num_trainable_parameters": 772074,
  "best_val_metrics": {
    "precision_macro": 0.9652114780948711,
    "recall_macro": 0.965093722559719,
    "f1_macro": 0.9651493495292012,
    "precision_micro": 0.9651908396946565,
    "recall_micro": 0.9651908396946565,
    "f1_micro": 0.9651908396946565,
    "accuracy": 0.9651908396946565,
    "hamming_loss": 0.03480916030534351,
    "no_defect_precision": 0.9646434885091337,
    "no_defect_recall": 0.9680662329982259,
    "no_defect_f1": 0.9663518299881936,
    "no_defect_tp": 1637,
    "no_defect_fp": 60,
    "no_defect_tn": 1524,
    "no_defect_fn": 54,
    "no_defect_support": 1691,
    "defect_precision": 0.9657794676806084,
    "defect_recall": 0.9621212121212122,
    "defect_f1": 0.9639468690702088,
    "defect_tp": 1524,
    "defect_fp": 54,
    "defect_tn": 1637,
    "defect_fn": 60,
    "defect_support": 1584
  },
  "test_metrics": {
    "precision_macro": 0.9682522643408252,
    "recall_macro": 0.9682522643408252,
    "f1_macro": 0.9682522643408252,
    "precision_micro": 0.9682539682539683,
    "recall_micro": 0.9682539682539683,
    "f1_micro": 0.9682539682539683,
    "accuracy": 0.9682539682539683,
    "hamming_loss": 0.031746031746031744,
    "no_defect_precision": 0.9684848484848485,
    "no_defect_recall": 0.9684848484848485,
    "no_defect_f1": 0.9684848484848485,
    "no_defect_tp": 1598,
    "no_defect_fp": 52,
    "no_defect_tn": 1574,
    "no_defect_fn": 52,
    "no_defect_support": 1650,
    "defect_precision": 0.968019680196802,
    "defect_recall": 0.968019680196802,
    "defect_f1": 0.968019680196802,
    "defect_tp": 1574,
    "defect_fp": 52,
    "defect_tn": 1598,
    "defect_fn": 52,
    "defect_support": 1626
  },
  "training_history": {
    "epoch": [
      1,
      2,
      3,
      4,
      5,
      6,
      7,
      8,
      9,
      10,
      11,
      12,
      13,
      14,
      15
    ],
    "train_loss": [
      0.38621641333881285,
      0.21075667428421674,
      0.18932714568895276,
      0.18847172726023645,
      0.18769518208054817,
      0.18246367927562743,
      0.1803799582076372,
      0.1788090521228114,
      0.17314293979039752,
      0.1759520724540475,
      0.17001027057422755,
      0.16372141706519547,
      0.16826751803254483,
      0.16783253203251372,
      0.16249599462086686
    ],
    "val_loss": [
      0.28724727865595084,
      0.15476128430320665,
      0.12383621988388208,
      0.10659146484417412,
      0.10928899930933347,
      0.10527033774325481,
      0.11541231589105266,
      0.10855588521091984,
      0.10067652706773235,
      0.09459354875322717,
      0.09840609323090085,
      0.10105700328802833,
      0.10022654993316302,
      0.09711959320478715,
      0.09689924457611945
    ]
  },
  "metrics_history": {
    "epoch": [
      1,
      2,
      3,
      4,
      5,
      6,
      7,
      8,
      9,
      10,
      11,
      12,
      13,
      14,
      15
    ],
    "train_metrics": [
      null,
      null,
      null,
      null,
      null,
      null,
      null,
      null,
      null,
      null,
      null,
      null,
      null,
      null,
      null
    ],
    "val_metrics": [
      {
        "precision_macro": 0.9150009734570705,
        "recall_macro": 0.915407213769869,
        "f1_macro": 0.9147976894459353,
        "precision_micro": 0.9148091603053435,
        "recall_micro": 0.9148091603053435,
        "f1_micro": 0.9148091603053435,
        "accuracy": 0.9148091603053435,
        "hamming_loss": 0.08519083969465649,
        "no_defect_precision": 0.9352651048088779,
        "no_defect_recall": 0.8971023063276168,
        "no_defect_f1": 0.9157862964080894,
        "no_defect_tp": 1517,
        "no_defect_fp": 105,
        "no_defect_tn": 1479,
        "no_defect_fn": 174,
        "no_defect_support": 1691,
        "defect_precision": 0.8947368421052632,
        "defect_recall": 0.9337121212121212,
        "defect_f1": 0.9138090824837812,
        "defect_tp": 1479,
        "defect_fp": 174,
        "defect_tn": 1517,
        "defect_fn": 105,
        "defect_support": 1584
      },
      {
        "precision_macro": 0.9517607553649092,
        "recall_macro": 0.9522434576396729,
        "f1_macro": 0.9517430868906078,
        "precision_micro": 0.9517557251908397,
        "recall_micro": 0.9517557251908397,
        "f1_micro": 0.9517557251908397,
        "accuracy": 0.9517557251908397,
        "hamming_loss": 0.048244274809160305,
        "no_defect_precision": 0.9682345754428833,
        "no_defect_recall": 0.9373151981076286,
        "no_defect_f1": 0.9525240384615384,
        "no_defect_tp": 1585,
        "no_defect_fp": 52,
        "no_defect_tn": 1532,
        "no_defect_fn": 106,
        "no_defect_support": 1691,
        "defect_precision": 0.9352869352869353,
        "defect_recall": 0.9671717171717171,
        "defect_f1": 0.9509621353196772,
        "defect_tp": 1532,
        "defect_fp": 106,
        "defect_tn": 1585,
        "defect_fn": 52,
        "defect_support": 1584
      },
      {
        "precision_macro": 0.9575333780860744,
        "recall_macro": 0.9580212234706617,
        "f1_macro": 0.9575448387030288,
        "precision_micro": 0.9575572519083969,
        "recall_micro": 0.9575572519083969,
        "f1_micro": 0.9575572519083969,
        "accuracy": 0.9575572519083969,
        "hamming_loss": 0.042442748091603054,
        "no_defect_precision": 0.973170731707317,
        "no_defect_recall": 0.9438202247191011,
        "no_defect_f1": 0.9582707895526869,
        "no_defect_tp": 1596,
        "no_defect_fp": 44,
        "no_defect_tn": 1540,
        "no_defect_fn": 95,
        "no_defect_support": 1691,
        "defect_precision": 0.9418960244648318,
        "defect_recall": 0.9722222222222222,
        "defect_f1": 0.9568188878533707,
        "defect_tp": 1540,
        "defect_fp": 95,
        "defect_tn": 1596,
        "defect_fn": 44,
        "defect_support": 1584
      },
      {
        "precision_macro": 0.9623006323800996,
        "recall_macro": 0.9626123371503323,
        "f1_macro": 0.9624168321091106,
        "precision_micro": 0.962442748091603,
        "recall_micro": 0.962442748091603,
        "f1_micro": 0.962442748091603,
        "accuracy": 0.962442748091603,
        "hamming_loss": 0.03755725190839695,
        "no_defect_precision": 0.9694610778443113,
        "no_defect_recall": 0.9574216439976345,
        "no_defect_f1": 0.9634037488842606,
        "no_defect_tp": 1619,
        "no_defect_fp": 51,
        "no_defect_tn": 1533,
        "no_defect_fn": 72,
        "no_defect_support": 1691,
        "defect_precision": 0.9551401869158879,
        "defect_recall": 0.9678030303030303,
        "defect_f1": 0.9614299153339605,
        "defect_tp": 1533,
        "defect_fp": 72,
        "defect_tn": 1619,
        "defect_fn": 51,
        "defect_support": 1584
      },
      {
        "precision_macro": 0.9598820872063836,
        "recall_macro": 0.9603267670794282,
        "f1_macro": 0.9599817176543564,
        "precision_micro": 0.96,
        "recall_micro": 0.96,
        "f1_micro": 0.96,
        "accuracy": 0.96,
        "hamming_loss": 0.04,
        "no_defect_precision": 0.971584038694075,
        "no_defect_recall": 0.9503252513305737,
        "no_defect_f1": 0.9608370702541106,
        "no_defect_tp": 1607,
        "no_defect_fp": 47,
        "no_defect_tn": 1537,
        "no_defect_fn": 84,
        "no_defect_support": 1691,
        "defect_precision": 0.9481801357186922,
        "defect_recall": 0.9703282828282829,
        "defect_f1": 0.9591263650546021,
        "defect_tp": 1537,
        "defect_fp": 84,
        "defect_tn": 1607,
        "defect_fn": 47,
        "defect_support": 1584
      },
      {
        "precision_macro": 0.9604661634724578,
        "recall_macro": 0.9607982919078425,
        "f1_macro": 0.9605847571630131,
        "precision_micro": 0.9606106870229008,
        "recall_micro": 0.9606106870229008,
        "f1_micro": 0.9606106870229008,
        "accuracy": 0.9606106870229008,
        "hamming_loss": 0.03938931297709924,
        "no_defect_precision": 0.9682254196642686,
        "no_defect_recall": 0.9550561797752809,
        "no_defect_f1": 0.9615957130098244,
        "no_defect_tp": 1615,
        "no_defect_fp": 53,
        "no_defect_tn": 1531,
        "no_defect_fn": 76,
        "no_defect_support": 1691,
        "defect_precision": 0.9527069072806472,
        "defect_recall": 0.9665404040404041,
        "defect_f1": 0.9595738013162018,
        "defect_tp": 1531,
        "defect_fp": 76,
        "defect_tn": 1615,
        "defect_fn": 53,
        "defect_support": 1584
      },
      {
        "precision_macro": 0.9559518481220395,
        "recall_macro": 0.956386940068933,
        "f1_macro": 0.9557198403741624,
        "precision_micro": 0.9557251908396946,
        "recall_micro": 0.9557251908396946,
        "f1_micro": 0.9557251908396946,
        "accuracy": 0.9557251908396946,
        "hamming_loss": 0.044274809160305344,
        "no_defect_precision": 0.9771604938271605,
        "no_defect_recall": 0.9361324659964518,
        "no_defect_f1": 0.9562065841135609,
        "no_defect_tp": 1583,
        "no_defect_fp": 37,
        "no_defect_tn": 1547,
        "no_defect_fn": 108,
        "no_defect_support": 1691,
        "defect_precision": 0.9347432024169184,
        "defect_recall": 0.9766414141414141,
        "defect_f1": 0.9552330966347639,
        "defect_tp": 1547,
        "defect_fp": 108,
        "defect_tn": 1583,
        "defect_fn": 37,
        "defect_support": 1584
      },
      {
        "precision_macro": 0.9600153501673004,
        "recall_macro": 0.9605065289201895,
        "f1_macro": 0.9599899131962271,
        "precision_micro": 0.96,
        "recall_micro": 0.96,
        "f1_micro": 0.96,
        "accuracy": 0.96,
        "hamming_loss": 0.04,
        "no_defect_precision": 0.9767726161369193,
        "no_defect_recall": 0.9450029568302779,
        "no_defect_f1": 0.9606251878569282,
        "no_defect_tp": 1598,
        "no_defect_fp": 38,
        "no_defect_tn": 1546,
        "no_defect_fn": 93,
        "no_defect_support": 1691,
        "defect_precision": 0.9432580841976815,
        "defect_recall": 0.976010101010101,
        "defect_f1": 0.9593546385355259,
        "defect_tp": 1546,
        "defect_fp": 93,
        "defect_tn": 1598,
        "defect_fn": 38,
        "defect_support": 1584
      },
      {
        "precision_macro": 0.9622994556653774,
        "recall_macro": 0.9626722577639195,
        "f1_macro": 0.9624203242305297,
        "precision_micro": 0.962442748091603,
        "recall_micro": 0.962442748091603,
        "f1_micro": 0.962442748091603,
        "accuracy": 0.962442748091603,
        "hamming_loss": 0.03755725190839695,
        "no_defect_precision": 0.9711538461538461,
        "no_defect_recall": 0.9556475458308693,
        "no_defect_f1": 0.963338301043219,
        "no_defect_tp": 1616,
        "no_defect_fp": 48,
        "no_defect_tn": 1536,
        "no_defect_fn": 75,
        "no_defect_support": 1691,
        "defect_precision": 0.9534450651769087,
        "defect_recall": 0.9696969696969697,
        "defect_f1": 0.9615023474178404,
        "defect_tp": 1536,
        "defect_fp": 75,
        "defect_tn": 1616,
        "defect_fn": 48,
        "defect_support": 1584
      },
      {
        "precision_macro": 0.9652114780948711,
        "recall_macro": 0.965093722559719,
        "f1_macro": 0.9651493495292012,
        "precision_micro": 0.9651908396946565,
        "recall_micro": 0.9651908396946565,
        "f1_micro": 0.9651908396946565,
        "accuracy": 0.9651908396946565,
        "hamming_loss": 0.03480916030534351,
        "no_defect_precision": 0.9646434885091337,
        "no_defect_recall": 0.9680662329982259,
        "no_defect_f1": 0.9663518299881936,
        "no_defect_tp": 1637,
        "no_defect_fp": 60,
        "no_defect_tn": 1524,
        "no_defect_fn": 54,
        "no_defect_support": 1691,
        "defect_precision": 0.9657794676806084,
        "defect_recall": 0.9621212121212122,
        "defect_f1": 0.9639468690702088,
        "defect_tp": 1524,
        "defect_fp": 54,
        "defect_tn": 1637,
        "defect_fn": 60,
        "defect_support": 1584
      },
      {
        "precision_macro": 0.963251731470707,
        "recall_macro": 0.9634194920822656,
        "f1_macro": 0.9633266070784687,
        "precision_micro": 0.9633587786259542,
        "recall_micro": 0.9633587786259542,
        "f1_micro": 0.9633587786259542,
        "accuracy": 0.9633587786259542,
        "hamming_loss": 0.0366412213740458,
        "no_defect_precision": 0.9672813801308745,
        "no_defect_recall": 0.9615612063867534,
        "no_defect_f1": 0.9644128113879004,
        "no_defect_tp": 1626,
        "no_defect_fp": 55,
        "no_defect_tn": 1529,
        "no_defect_fn": 65,
        "no_defect_support": 1691,
        "defect_precision": 0.9592220828105396,
        "defect_recall": 0.9652777777777778,
        "defect_f1": 0.9622404027690371,
        "defect_tp": 1529,
        "defect_fp": 65,
        "defect_tn": 1626,
        "defect_fn": 55,
        "defect_support": 1584
      },
      {
        "precision_macro": 0.9632197426640914,
        "recall_macro": 0.9636192274608892,
        "f1_macro": 0.9633385125846853,
        "precision_micro": 0.9633587786259542,
        "recall_micro": 0.9633587786259542,
        "f1_micro": 0.9633587786259542,
        "accuracy": 0.9633587786259542,
        "hamming_loss": 0.0366412213740458,
        "no_defect_precision": 0.9729078868151716,
        "no_defect_recall": 0.9556475458308693,
        "no_defect_f1": 0.964200477326969,
        "no_defect_tp": 1616,
        "no_defect_fp": 45,
        "no_defect_tn": 1539,
        "no_defect_fn": 75,
        "no_defect_support": 1691,
        "defect_precision": 0.9535315985130112,
        "defect_recall": 0.9715909090909091,
        "defect_f1": 0.9624765478424016,
        "defect_tp": 1539,
        "defect_fp": 75,
        "defect_tn": 1616,
        "defect_fn": 45,
        "defect_support": 1584
      },
      {
        "precision_macro": 0.9626089298410134,
        "recall_macro": 0.9630078878674384,
        "f1_macro": 0.9627274877944301,
        "precision_micro": 0.9627480916030534,
        "recall_micro": 0.9627480916030534,
        "f1_micro": 0.9627480916030534,
        "accuracy": 0.9627480916030534,
        "hamming_loss": 0.037251908396946566,
        "no_defect_precision": 0.9723058398555088,
        "no_defect_recall": 0.9550561797752809,
        "no_defect_f1": 0.9636038186157518,
        "no_defect_tp": 1615,
        "no_defect_fp": 46,
        "no_defect_tn": 1538,
        "no_defect_fn": 76,
        "no_defect_support": 1691,
        "defect_precision": 0.952912019826518,
        "defect_recall": 0.9709595959595959,
        "defect_f1": 0.9618511569731082,
        "defect_tp": 1538,
        "defect_fp": 76,
        "defect_tn": 1615,
        "defect_fn": 46,
        "defect_support": 1584
      },
      {
        "precision_macro": 0.9644496268656717,
        "recall_macro": 0.9647020918827542,
        "f1_macro": 0.9645527847197962,
        "precision_micro": 0.9645801526717557,
        "recall_micro": 0.9645801526717557,
        "f1_micro": 0.9645801526717557,
        "accuracy": 0.9645801526717557,
        "hamming_loss": 0.035419847328244276,
        "no_defect_precision": 0.9701492537313433,
        "no_defect_recall": 0.960969840331165,
        "no_defect_f1": 0.9655377302436126,
        "no_defect_tp": 1625,
        "no_defect_fp": 50,
        "no_defect_tn": 1534,
        "no_defect_fn": 66,
        "no_defect_support": 1691,
        "defect_precision": 0.95875,
        "defect_recall": 0.9684343434343434,
        "defect_f1": 0.9635678391959799,
        "defect_tp": 1534,
        "defect_fp": 66,
        "defect_tn": 1625,
        "defect_fn": 50,
        "defect_support": 1584
      },
      {
        "precision_macro": 0.9644496268656717,
        "recall_macro": 0.9647020918827542,
        "f1_macro": 0.9645527847197962,
        "precision_micro": 0.9645801526717557,
        "recall_micro": 0.9645801526717557,
        "f1_micro": 0.9645801526717557,
        "accuracy": 0.9645801526717557,
        "hamming_loss": 0.035419847328244276,
        "no_defect_precision": 0.9701492537313433,
        "no_defect_recall": 0.960969840331165,
        "no_defect_f1": 0.9655377302436126,
        "no_defect_tp": 1625,
        "no_defect_fp": 50,
        "no_defect_tn": 1534,
        "no_defect_fn": 66,
        "no_defect_support": 1691,
        "defect_precision": 0.95875,
        "defect_recall": 0.9684343434343434,
        "defect_f1": 0.9635678391959799,
        "defect_tp": 1534,
        "defect_fp": 66,
        "defect_tn": 1625,
        "defect_fn": 50,
        "defect_support": 1584
      }
    ],
    "test_metrics": [
      {
        "precision_macro": 0.9682522643408252,
        "recall_macro": 0.9682522643408252,
        "f1_macro": 0.9682522643408252,
        "precision_micro": 0.9682539682539683,
        "recall_micro": 0.9682539682539683,
        "f1_micro": 0.9682539682539683,
        "accuracy": 0.9682539682539683,
        "hamming_loss": 0.031746031746031744,
        "no_defect_precision": 0.9684848484848485,
        "no_defect_recall": 0.9684848484848485,
        "no_defect_f1": 0.9684848484848485,
        "no_defect_tp": 1598,
        "no_defect_fp": 52,
        "no_defect_tn": 1574,
        "no_defect_fn": 52,
        "no_defect_support": 1650,
        "defect_precision": 0.968019680196802,
        "defect_recall": 0.968019680196802,
        "defect_f1": 0.968019680196802,
        "defect_tp": 1574,
        "defect_fp": 52,
        "defect_tn": 1598,
        "defect_fn": 52,
        "defect_support": 1626
      }
    ]
  }
}